openai_zeusdb/__init__.py
openai_zeusdb-0.0.0.dist-info/METADATA
openai_zeusdb-0.0.0.dist-info/WHEEL
openai_zeusdb-0.0.0.dist-info/top_level.txt
openai_zeusdb-0.0.0.dist-info/RECORD
