Metadata-Version: 2.4
Name: openai-zeusdb
Version: 0.0.0
Summary: Build production-ready RAG fast: OpenAI embeddings + ZeusDB vector storage with enterprise performance.
